rbseverity/__init__.py
rbseverity/extension.py
rbseverity/static/css/default.min.00d2be5a5b5e.css
rbseverity/static/css/default.min.css
rbseverity/static/css/severity.69eada437e3f.less
rbseverity/static/css/severity.css
rbseverity/static/css/severity.css.map
rbseverity/static/css/severity.less
rbseverity/static/js/severity-review.min.5362852ce295.js
rbseverity/static/js/severity-review.min.js
rbseverity/static/js/severity.es6.5a9387077f08.js
rbseverity/static/js/severity.es6.js
rbseverity/static/js/severity.js
rbseverity/static/js/severity.js.map
rbseverity-0.6.dist-info/METADATA
rbseverity-0.6.dist-info/WHEEL
rbseverity-0.6.dist-info/entry_points.txt
rbseverity-0.6.dist-info/top_level.txt
rbseverity-0.6.dist-info/RECORD
