Metadata-Version: 1.2
Name: rbseverity
Version: 0.6
Summary: Comment severity fields for Review Board.
Home-page: http://www.reviewboard.org/
Author: Beanbag, Inc.
Author-email: support@beanbaginc.com
Maintainer: Beanbag, Inc.
Maintainer-email: support@beanbaginc.com
License: UNKNOWN
Platform: UNKNOWN
Classifier: Development Status :: 4 - Beta
Classifier: Environment :: Web Environment
Classifier: Framework :: Review Board
Classifier: Intended Audience :: Developers
Classifier: License :: OSI Approved :: MIT License
Classifier: Natural Language :: English
Classifier: Operating System :: OS Independent
Classifier: Programming Language :: Python
